khulnasoft_analyze_sdk/__init__.py
khulnasoft_analyze_sdk/_account_api.py
khulnasoft_analyze_sdk/_api.py
khulnasoft_analyze_sdk/_endpoint_analysis_api.py
khulnasoft_analyze_sdk/_operation.py
khulnasoft_analyze_sdk/_util.py
khulnasoft_analyze_sdk/account.py
khulnasoft_analyze_sdk/alerts.py
khulnasoft_analyze_sdk/alerts_results.py
khulnasoft_analyze_sdk/analyses_history.py
khulnasoft_analyze_sdk/analyses_results.py
khulnasoft_analyze_sdk/analysis.py
khulnasoft_analyze_sdk/api.py
khulnasoft_analyze_sdk/base_analysis.py
khulnasoft_analyze_sdk/consts.py
khulnasoft_analyze_sdk/endpoint_analysis.py
khulnasoft_analyze_sdk/errors.py
khulnasoft_analyze_sdk/family.py
khulnasoft_analyze_sdk/history_results.py
khulnasoft_analyze_sdk/index.py
khulnasoft_analyze_sdk/operation.py
khulnasoft_analyze_sdk/sub_analysis.py
khulnasoft_analyze_sdk/util.py
khulnasoft_analyze_sdk-1.21.dist-info/LICENSE
khulnasoft_analyze_sdk-1.21.dist-info/METADATA
khulnasoft_analyze_sdk-1.21.dist-info/WHEEL
khulnasoft_analyze_sdk-1.21.dist-info/top_level.txt
khulnasoft_analyze_sdk-1.21.dist-info/RECORD
