Metadata-Version: 2.1
Name: khulnasoft_analyze_sdk
Version: 1.21
Summary: Khulnasoft Analyze SDK
Home-page: https://github.com/khulnasoft/analyze-python-sdk
Author: Khulnasoft Labs ltd.
Author-email: info@khulnasoft.com
License: Apache 2.0
Keywords: khulnasoft
Classifier: License :: OSI Approved :: Apache Software License
Classifier: Programming Language :: Python :: 3.8
Classifier: Programming Language :: Python :: 3.9
Classifier: Programming Language :: Python :: 3.10
Classifier: Programming Language :: Python :: 3.11
Classifier: Programming Language :: Python :: 3.12
Requires-Python: !=3.0.*,!=3.1.*,!=3.2.*,!=3.3.*,!=3.4.*,!=3.5.*,!=3.6.*,!=3.7.*
License-File: LICENSE
Requires-Dist: requests <3,>=2.29.0
